xpflow.py
xpflow-0.8.dist-info/LICENSE
xpflow-0.8.dist-info/METADATA
xpflow-0.8.dist-info/WHEEL
xpflow-0.8.dist-info/top_level.txt
xpflow-0.8.dist-info/RECORD
