Metadata-Version: 2.1
Name: xpflow
Version: 0.8
Summary: Utilities for representing experiments with classes
Home-page: https://github.com/sileod/xpflow
Author: sileod
License: MIT
License-File: LICENSE
Requires-Dist: easydict
Requires-Dist: sorcery
